graph_layout/__init__.py
graph_layout/_speedups.cpython-313-x86_64-linux-gnu.so
graph_layout/base.py
graph_layout/metrics.py
graph_layout/preprocessing.py
graph_layout/py.typed
graph_layout/types.py
graph_layout/validation.py
graph_layout/basic/__init__.py
graph_layout/basic/random.py
graph_layout/bipartite/__init__.py
graph_layout/bipartite/bipartite.py
graph_layout/circular/__init__.py
graph_layout/circular/circular.py
graph_layout/circular/shell.py
graph_layout/cola/__init__.py
graph_layout/cola/_shortestpaths_py.py
graph_layout/cola/adapter.py
graph_layout/cola/batch.py
graph_layout/cola/descent.py
graph_layout/cola/geom.py
graph_layout/cola/gridrouter.py
graph_layout/cola/handledisconnected.py
graph_layout/cola/layout.py
graph_layout/cola/layout3d.py
graph_layout/cola/linklengths.py
graph_layout/cola/powergraph.py
graph_layout/cola/pqueue.py
graph_layout/cola/rbtree.py
graph_layout/cola/rectangle.py
graph_layout/cola/shortestpaths.py
graph_layout/cola/vpsc.py
graph_layout/export/__init__.py
graph_layout/export/dot.py
graph_layout/export/graphml.py
graph_layout/export/svg.py
graph_layout/force/__init__.py
graph_layout/force/force_atlas2.py
graph_layout/force/fruchterman_reingold.py
graph_layout/force/kamada_kawai.py
graph_layout/force/spring.py
graph_layout/force/yifan_hu.py
graph_layout/hierarchical/__init__.py
graph_layout/hierarchical/radial_tree.py
graph_layout/hierarchical/reingold_tilford.py
graph_layout/hierarchical/sugiyama.py
graph_layout/orthogonal/__init__.py
graph_layout/orthogonal/compaction.py
graph_layout/orthogonal/compaction_ilp.py
graph_layout/orthogonal/giotto.py
graph_layout/orthogonal/kandinsky.py
graph_layout/orthogonal/orthogonalization.py
graph_layout/orthogonal/planarization.py
graph_layout/orthogonal/types.py
graph_layout/spatial/__init__.py
graph_layout/spatial/quadtree.py
graph_layout/spectral/__init__.py
graph_layout/spectral/spectral.py
graph_layout-0.1.7.dist-info/METADATA
graph_layout-0.1.7.dist-info/WHEEL
graph_layout-0.1.7.dist-info/top_level.txt
graph_layout-0.1.7.dist-info/RECORD
graph_layout-0.1.7.dist-info/licenses/LICENSE
