Metadata-Version: 2.4
Name: graph-layout
Version: 0.1.7
Summary: A collection of graph layout algorithms in Python
Author-email: Shakeeb Alireza <me@example.org>
License-Expression: MIT
Project-URL: Homepage, https://github.com/shakfu/graph-layout
Project-URL: Repository, https://github.com/shakfu/graph-layout
Project-URL: Documentation, https://github.com/shakfu/graph-layout
Keywords: graph,layout,constraints,optimization,visualization,cola,force-directed
Classifier: Development Status :: 3 - Alpha
Classifier: Intended Audience :: Developers
Classifier: Programming Language :: Python :: 3
Classifier: Programming Language :: Python :: 3.9
Classifier: Programming Language :: Python :: 3.10
Classifier: Programming Language :: Python :: 3.11
Classifier: Programming Language :: Python :: 3.12
Classifier: Programming Language :: Python :: 3.13
Classifier: Programming Language :: Python :: 3.14
Classifier: Topic :: Scientific/Engineering :: Visualization
Requires-Python: >=3.9
License-File: LICENSE
Requires-Dist: numpy>=1.20.0
Requires-Dist: sortedcontainers>=2.4.0
Provides-Extra: ilp
Requires-Dist: scipy>=1.9.0; extra == "ilp"
Dynamic: license-file
